[{"name":"Acrobatics","stat":"DEX","useuntrained":"Can be used even when untrained."},{"name":"Appraise","stat":"INT","useuntrained":"Can be used even when untrained."},{"name":"Bluff","stat":"CHA","useuntrained":"Can be used even when untrained."},{"name":"Climb","stat":"STR","useuntrained":"Can be used even when untrained."},{"name":"Craft (Alchemy)","stat":"INT","useuntrained":"Can be used even when untrained."},{"name":"Craft (Armor)","stat":"INT","useuntrained":"Can be used even when untrained."},{"name":"Craft (Baskets)","stat":"INT","useuntrained":"Can be used even when untrained."},{"name":"Craft (Blacksmithing)","stat":"INT","useuntrained":"Can be used even when untrained."},{"name":"Craft (Books)","stat":"INT","useuntrained":"Can be used even when untrained."},{"name":"Craft (Bows)","stat":"INT","useuntrained":"Can be used even when untrained."},{"name":"Craft (Calligraphy)","stat":"INT","useuntrained":"Can be used even when untrained."},{"name":"Craft (Carpentry)","stat":"INT","useuntrained":"Can be used even when untrained."},{"name":"Craft (Cloth)","stat":"INT","useuntrained":"Can be used even when untrained."},{"name":"Craft (Clothing)","stat":"INT","useuntrained":"Can be used even when untrained."},{"name":"Craft (Gemcutting)","stat":"INT","useuntrained":"Can be used even when untrained."},{"name":"Craft (Glass)","stat":"INT","useuntrained":"Can be used even when untrained."},{"name":"Craft (Jewelry)","stat":"INT","useuntrained":"Can be used even when untrained."},{"name":"Craft (Leather)","stat":"INT","useuntrained":"Can be used even when untrained."},{"name":"Craft (Locks)","stat":"INT","useuntrained":"Can be used even when untrained."},{"name":"Craft (Paintings)","stat":"INT","useuntrained":"Can be used even when untrained."},{"name":"Craft (Pottery)","stat":"INT","useuntrained":"Can be used even when untrained."},{"name":"Craft (Sculptures)","stat":"INT","useuntrained":"Can be used even when untrained."},{"name":"Craft (Ships)","stat":"INT","useuntrained":"Can be used even when untrained."},{"name":"Craft (Shoes)","stat":"INT","useuntrained":"Can be used even when untrained."},{"name":"Craft (Stonemasonry)","stat":"INT","useuntrained":"Can be used even when untrained."},{"name":"Craft (Traps)","stat":"INT","useuntrained":"Can be used even when untrained."},{"name":"Craft (Weapons)","stat":"INT","useuntrained":"Can be used even when untrained."},{"name":"Craft (Untrained)","stat":"INT","useuntrained":"Can be used even when untrained."},{"name":"Diplomacy","stat":"CHA","useuntrained":"Can be used even when untrained."},{"name":"Disable Device","stat":"DEX","useuntrained":"Can be used even when untrained."},{"name":"Disguise","stat":"CHA","useuntrained":"Can be used even when untrained."},{"name":"Escape Artist","stat":"DEX","useuntrained":"Can be used even when untrained."},{"name":"Fly","stat":"DEX","useuntrained":"Can be used even when untrained."},{"name":"Handle Animal","stat":"CHA","useuntrained":"Can be used even when untrained."},{"name":"Heal","stat":"WIS","useuntrained":"Can be used even when untrained."},{"name":"Intimidate","stat":"CHA","useuntrained":"Can be used even when untrained."},{"name":"Knowledge (Arcana)","stat":"INT","useuntrained":"Can be used even when untrained."},{"name":"Knowledge (Dungeoneering)","stat":"INT","useuntrained":"Can be used even when untrained."},{"name":"Knowledge (Engineering)","stat":"INT","useuntrained":"Can be used even when untrained."},{"name":"Knowledge (Geography)","stat":"INT","useuntrained":"Can be used even when untrained."},{"name":"Knowledge (History)","stat":"INT","useuntrained":"Can be used even when untrained."},{"name":"Knowledge (Local)","stat":"INT","useuntrained":"Can be used even when untrained."},{"name":"Knowledge (Nature)","stat":"INT","useuntrained":"Can be used even when untrained."},{"name":"Knowledge (Nobility)","stat":"INT","useuntrained":"Can be used even when untrained."},{"name":"Knowledge (Planes)","stat":"INT","useuntrained":"Can be used even when untrained."},{"name":"Knowledge (Religion)","stat":"INT","useuntrained":"Can be used even when untrained."},{"name":"Knowledge (Untrained)","stat":"INT","useuntrained":"Can be used even when untrained."},{"name":"Linguistics","stat":"INT","useuntrained":"Can be used even when untrained."},{"name":"Perception","stat":"WIS","useuntrained":"Can be used even when untrained."},{"name":"Perform (Act)","stat":"CHA","useuntrained":"Can be used even when untrained."},{"name":"Perform (Comedy)","stat":"CHA","useuntrained":"Can be used even when untrained."},{"name":"Perform (Dance)","stat":"CHA","useuntrained":"Can be used even when untrained."},{"name":"Perform (Keyboard Instruments)","stat":"CHA","useuntrained":"Can be used even when untrained."},{"name":"Perform (Oratory)","stat":"CHA","useuntrained":"Can be used even when untrained."},{"name":"Perform (Percussion Instruments)","stat":"CHA","useuntrained":"Can be used even when untrained."},{"name":"Perform (Sing)","stat":"CHA","useuntrained":"Can be used even when untrained."},{"name":"Perform (String Instruments)","stat":"CHA","useuntrained":"Can be used even when untrained."},{"name":"Perform (Wind Instruments)","stat":"CHA","useuntrained":"Can be used even when untrained."},{"name":"Perform (Untrained)","stat":"CHA","useuntrained":"Can be used even when untrained."},{"name":"Profession (Architect)","stat":"WIS","useuntrained":"Can be used even when untrained."},{"name":"Profession (Baker)","stat":"WIS","useuntrained":"Can be used even when untrained."},{"name":"Profession (Barrister)","stat":"WIS","useuntrained":"Can be used even when untrained."},{"name":"Profession (Brewer)","stat":"WIS","useuntrained":"Can be used even when untrained."},{"name":"Profession (Butcher)","stat":"WIS","useuntrained":"Can be used even when untrained."},{"name":"Profession (Clerk)","stat":"WIS","useuntrained":"Can be used even when untrained."},{"name":"Profession (Cook)","stat":"WIS","useuntrained":"Can be used even when untrained."},{"name":"Profession (Courtesan)","stat":"WIS","useuntrained":"Can be used even when untrained."},{"name":"Profession (Driver)","stat":"WIS","useuntrained":"Can be used even when untrained."},{"name":"Profession (Engineer)","stat":"WIS","useuntrained":"Can be used even when untrained."},{"name":"Profession (Farmer)","stat":"WIS","useuntrained":"Can be used even when untrained."},{"name":"Profession (Fisherman)","stat":"WIS","useuntrained":"Can be used even when untrained."},{"name":"Profession (Gambler)","stat":"WIS","useuntrained":"Can be used even when untrained."},{"name":"Profession (Gardener)","stat":"WIS","useuntrained":"Can be used even when untrained."},{"name":"Profession (Herbalist)","stat":"WIS","useuntrained":"Can be used even when untrained."},{"name":"Profession (Innkeeper)","stat":"WIS","useuntrained":"Can be used even when untrained."},{"name":"Profession (Librarian)","stat":"WIS","useuntrained":"Can be used even when untrained."},{"name":"Profession (Merchant)","stat":"WIS","useuntrained":"Can be used even when untrained."},{"name":"Profession (Midwife)","stat":"WIS","useuntrained":"Can be used even when untrained."},{"name":"Profession (Miller)","stat":"WIS","useuntrained":"Can be used even when untrained."},{"name":"Profession (Miner)","stat":"WIS","useuntrained":"Can be used even when untrained."},{"name":"Profession (Porter)","stat":"WIS","useuntrained":"Can be used even when untrained."},{"name":"Profession (Sailor)","stat":"WIS","useuntrained":"Can be used even when untrained."},{"name":"Profession (Scribe)","stat":"WIS","useuntrained":"Can be used even when untrained."},{"name":"Profession (Shepherd)","stat":"WIS","useuntrained":"Can be used even when untrained."},{"name":"Profession (Soldier)","stat":"WIS","useuntrained":"Can be used even when untrained."},{"name":"Profession (Soothsayer)","stat":"WIS","useuntrained":"Can be used even when untrained."},{"name":"Profession (Stable Master)","stat":"WIS","useuntrained":"Can be used even when untrained."},{"name":"Profession (Tanner)","stat":"WIS","useuntrained":"Can be used even when untrained."},{"name":"Profession (Trapper)","stat":"WIS","useuntrained":"Can be used even when untrained."},{"name":"Profession (Woodcutter)","stat":"WIS","useuntrained":"Can be used even when untrained."},{"name":"Ride","stat":"DEX","useuntrained":"Can be used even when untrained."},{"name":"Sense Motive","stat":"WIS","useuntrained":"Can be used even when untrained."},{"name":"Sleight of Hand","stat":"DEX","useuntrained":"Can be used even when untrained."},{"name":"Spellcraft","stat":"INT","useuntrained":"Can be used even when untrained."},{"name":"Stealth","stat":"DEX","useuntrained":"Can be used even when untrained."},{"name":"Survival","stat":"WIS","useuntrained":"Can be used even when untrained."},{"name":"Swim","stat":"STR","useuntrained":"Can be used even when untrained."},{"name":"Use Magic Device","stat":"CHA","useuntrained":"Can be used even when untrained."},{"name":"Untrained Strength","stat":"STR","useuntrained":"Can be used even when untrained."},{"name":"Untrained Dexterity","stat":"DEX","useuntrained":"Can be used even when untrained."},{"name":"Untrained Intelligence","stat":"INT","useuntrained":"Can be used even when untrained."},{"name":"Untrained Wisdom","stat":"WIS","useuntrained":"Can be used even when untrained."},{"name":"Untrained Charisma","stat":"CHA","useuntrained":"Can be used even when untrained."},{"name":"Profession (Untrained)","stat":"WIS","useuntrained":"Can be used even when untrained."}]